{"metadata": {"dbt_schema_version": "https://schemas.getdbt.com/dbt/catalog/v1.json", "dbt_version": "1.8.6", "generated_at": "2024-09-20T12:17:56.202870Z", "invocation_id": "1e64f3e0-b181-4d31-af46-f843294bfa28", "env": {}}, "nodes": {"model.medallion_dbt_spark.dim_customer": {"metadata": {"type": "table", "schema": "saleslt", "name": "dim_customer", "database": "hive_metastore", "comment": null, "owner": "root"}, "columns": {"customer_sk": {"type": "integer", "index": 0, "name": "customer_sk", "comment": null}, "CustomerId": {"type": "integer", "index": 1, "name": "CustomerId", "comment": null}, "fullname": {"type": "string", "index": 2, "name": "fullname", "comment": null}, "AddressID": {"type": "integer", "index": 3, "name": "AddressID", "comment": null}, "AddressType": {"type": "string", "index": 4, "name": "AddressType", "comment": null}, "AddressLine1": {"type": "string", "index": 5, "name": "AddressLine1", "comment": null}, "City": {"type": "string", "index": 6, "name": "City", "comment": null}, "StateProvince": {"type": "string", "index": 7, "name": "StateProvince", "comment": null}, "CountryRegion": {"type": "string", "index": 8, "name": "CountryRegion", "comment": null}, "PostalCode": {"type": "string", "index": 9, "name": "PostalCode", "comment": null}}, "stats": {"has_stats": {"id": "has_stats", "label": "Has Stats?", "value": false, "include": false, "description": "Indicates whether there are statistics for this table"}}, "unique_id": "model.medallion_dbt_spark.dim_customer"}, "model.medallion_dbt_spark.dim_product": {"metadata": {"type": "table", "schema": "saleslt", "name": "dim_product", "database": "hive_metastore", "comment": null, "owner": "root"}, "columns": {"product_sk": {"type": "integer", "index": 0, "name": "product_sk", "comment": null}, "product_name": {"type": "string", "index": 1, "name": "product_name", "comment": null}, "standardCost": {"type": "decimal(19,4)", "index": 2, "name": "standardCost", "comment": null}, "listPrice": {"type": "decimal(19,4)", "index": 3, "name": "listPrice", "comment": null}, "size": {"type": "string", "index": 4, "name": "size", "comment": null}, "weight": {"type": "decimal(8,2)", "index": 5, "name": "weight", "comment": null}, "model": {"type": "string", "index": 6, "name": "model", "comment": null}, "description": {"type": "string", "index": 7, "name": "description", "comment": null}, "sellstartdate": {"type": "timestamp", "index": 8, "name": "sellstartdate", "comment": null}, "sellenddate": {"type": "timestamp", "index": 9, "name": "sellenddate", "comment": null}, "discontinueddate": {"type": "timestamp", "index": 10, "name": "discontinueddate", "comment": null}}, "stats": {"has_stats": {"id": "has_stats", "label": "Has Stats?", "value": false, "include": false, "description": "Indicates whether there are statistics for this table"}}, "unique_id": "model.medallion_dbt_spark.dim_product"}, "model.medallion_dbt_spark.my_first_dbt_model": {"metadata": {"type": "table", "schema": "saleslt", "name": "my_first_dbt_model", "database": "hive_metastore", "comment": null, "owner": "root"}, "columns": {"id": {"type": "integer", "index": 0, "name": "id", "comment": null}}, "stats": {"has_stats": {"id": "has_stats", "label": "Has Stats?", "value": false, "include": false, "description": "Indicates whether there are statistics for this table"}}, "unique_id": "model.medallion_dbt_spark.my_first_dbt_model"}, "model.medallion_dbt_spark.my_second_dbt_model": {"metadata": {"type": "view", "schema": "saleslt", "name": "my_second_dbt_model", "database": "hive_metastore", "comment": null, "owner": "root"}, "columns": {"id": {"type": "integer", "index": 0, "name": "id", "comment": null}}, "stats": {"has_stats": {"id": "has_stats", "label": "Has Stats?", "value": false, "include": false, "description": "Indicates whether there are statistics for this table"}}, "unique_id": "model.medallion_dbt_spark.my_second_dbt_model"}, "model.medallion_dbt_spark.sales": {"metadata": {"type": "table", "schema": "saleslt", "name": "sales", "database": "hive_metastore", "comment": null, "owner": "root"}, "columns": {"SalesOrderID": {"type": "integer", "index": 0, "name": "SalesOrderID", "comment": null}, "SalesOrderDetailID": {"type": "integer", "index": 1, "name": "SalesOrderDetailID", "comment": null}, "OrderQty": {"type": "integer", "index": 2, "name": "OrderQty", "comment": null}, "ProductID": {"type": "integer", "index": 3, "name": "ProductID", "comment": null}, "UnitPrice": {"type": "decimal(19,4)", "index": 4, "name": "UnitPrice", "comment": null}, "UnitPriceDiscount": {"type": "decimal(19,4)", "index": 5, "name": "UnitPriceDiscount", "comment": null}, "LineTotal": {"type": "decimal(38,6)", "index": 6, "name": "LineTotal", "comment": null}, "Name": {"type": "string", "index": 7, "name": "Name", "comment": null}, "ProductNumber": {"type": "string", "index": 8, "name": "ProductNumber", "comment": null}, "Color": {"type": "string", "index": 9, "name": "Color", "comment": null}, "StandardCost": {"type": "decimal(19,4)", "index": 10, "name": "StandardCost", "comment": null}, "ListPrice": {"type": "decimal(19,4)", "index": 11, "name": "ListPrice", "comment": null}, "Size": {"type": "string", "index": 12, "name": "Size", "comment": null}, "Weight": {"type": "decimal(8,2)", "index": 13, "name": "Weight", "comment": null}, "SellStartDate": {"type": "timestamp", "index": 14, "name": "SellStartDate", "comment": null}, "SellEndDate": {"type": "timestamp", "index": 15, "name": "SellEndDate", "comment": null}, "DiscontinuedDate": {"type": "timestamp", "index": 16, "name": "DiscontinuedDate", "comment": null}, "ThumbNailPhoto": {"type": "binary", "index": 17, "name": "ThumbNailPhoto", "comment": null}, "ThumbnailPhotoFileName": {"type": "string", "index": 18, "name": "ThumbnailPhotoFileName", "comment": null}, "RevisionNumber": {"type": "integer", "index": 19, "name": "RevisionNumber", "comment": null}, "OrderDate": {"type": "timestamp", "index": 20, "name": "OrderDate", "comment": null}, "DueDate": {"type": "timestamp", "index": 21, "name": "DueDate", "comment": null}, "ShipDate": {"type": "timestamp", "index": 22, "name": "ShipDate", "comment": null}, "Status": {"type": "integer", "index": 23, "name": "Status", "comment": null}, "OnlineOrderFlag": {"type": "boolean", "index": 24, "name": "OnlineOrderFlag", "comment": null}, "SalesOrderNumber": {"type": "string", "index": 25, "name": "SalesOrderNumber", "comment": null}, "PurchaseOrderNumber": {"type": "string", "index": 26, "name": "PurchaseOrderNumber", "comment": null}, "AccountNumber": {"type": "string", "index": 27, "name": "AccountNumber", "comment": null}, "CustomerID": {"type": "integer", "index": 28, "name": "CustomerID", "comment": null}, "ShipToAddressID": {"type": "integer", "index": 29, "name": "ShipToAddressID", "comment": null}, "BillToAddressID": {"type": "integer", "index": 30, "name": "BillToAddressID", "comment": null}, "ShipMethod": {"type": "string", "index": 31, "name": "ShipMethod", "comment": null}, "CreditCardApprovalCode": {"type": "string", "index": 32, "name": "CreditCardApprovalCode", "comment": null}, "SubTotal": {"type": "decimal(19,4)", "index": 33, "name": "SubTotal", "comment": null}, "TaxAmt": {"type": "decimal(19,4)", "index": 34, "name": "TaxAmt", "comment": null}, "Freight": {"type": "decimal(19,4)", "index": 35, "name": "Freight", "comment": null}, "TotalDue": {"type": "decimal(19,4)", "index": 36, "name": "TotalDue", "comment": null}, "Comment": {"type": "string", "index": 37, "name": "Comment", "comment": null}}, "stats": {"has_stats": {"id": "has_stats", "label": "Has Stats?", "value": false, "include": false, "description": "Indicates whether there are statistics for this table"}}, "unique_id": "model.medallion_dbt_spark.sales"}, "snapshot.medallion_dbt_spark.address_snapshot": {"metadata": {"type": "table", "schema": "snapshots", "name": "address_snapshot", "database": "hive_metastore", "comment": null, "owner": "root"}, "columns": {"AddressID": {"type": "integer", "index": 0, "name": "AddressID", "comment": null}, "AddressLine1": {"type": "string", "index": 1, "name": "AddressLine1", "comment": null}, "AddressLine2": {"type": "string", "index": 2, "name": "AddressLine2", "comment": null}, "City": {"type": "string", "index": 3, "name": "City", "comment": null}, "StateProvince": {"type": "string", "index": 4, "name": "StateProvince", "comment": null}, "CountryRegion": {"type": "string", "index": 5, "name": "CountryRegion", "comment": null}, "PostalCode": {"type": "string", "index": 6, "name": "PostalCode", "comment": null}, "dbt_scd_id": {"type": "string", "index": 7, "name": "dbt_scd_id", "comment": null}, "dbt_updated_at": {"type": "timestamp", "index": 8, "name": "dbt_updated_at", "comment": null}, "dbt_valid_from": {"type": "timestamp", "index": 9, "name": "dbt_valid_from", "comment": null}, "dbt_valid_to": {"type": "timestamp", "index": 10, "name": "dbt_valid_to", "comment": null}}, "stats": {"has_stats": {"id": "has_stats", "label": "Has Stats?", "value": false, "include": false, "description": "Indicates whether there are statistics for this table"}}, "unique_id": "snapshot.medallion_dbt_spark.address_snapshot"}, "snapshot.medallion_dbt_spark.customer_snapshot": {"metadata": {"type": "table", "schema": "snapshots", "name": "customer_snapshot", "database": "hive_metastore", "comment": null, "owner": "root"}, "columns": {"CustomerId": {"type": "integer", "index": 0, "name": "CustomerId", "comment": null}, "NameStyle": {"type": "boolean", "index": 1, "name": "NameStyle", "comment": null}, "Title": {"type": "string", "index": 2, "name": "Title", "comment": null}, "FirstName": {"type": "string", "index": 3, "name": "FirstName", "comment": null}, "MiddleName": {"type": "string", "index": 4, "name": "MiddleName", "comment": null}, "LastName": {"type": "string", "index": 5, "name": "LastName", "comment": null}, "Suffix": {"type": "string", "index": 6, "name": "Suffix", "comment": null}, "CompanyName": {"type": "string", "index": 7, "name": "CompanyName", "comment": null}, "SalesPerson": {"type": "string", "index": 8, "name": "SalesPerson", "comment": null}, "EmailAddress": {"type": "string", "index": 9, "name": "EmailAddress", "comment": null}, "Phone": {"type": "string", "index": 10, "name": "Phone", "comment": null}, "PasswordHash": {"type": "string", "index": 11, "name": "PasswordHash", "comment": null}, "PasswordSalt": {"type": "string", "index": 12, "name": "PasswordSalt", "comment": null}, "dbt_scd_id": {"type": "string", "index": 13, "name": "dbt_scd_id", "comment": null}, "dbt_updated_at": {"type": "timestamp", "index": 14, "name": "dbt_updated_at", "comment": null}, "dbt_valid_from": {"type": "timestamp", "index": 15, "name": "dbt_valid_from", "comment": null}, "dbt_valid_to": {"type": "timestamp", "index": 16, "name": "dbt_valid_to", "comment": null}}, "stats": {"has_stats": {"id": "has_stats", "label": "Has Stats?", "value": false, "include": false, "description": "Indicates whether there are statistics for this table"}}, "unique_id": "snapshot.medallion_dbt_spark.customer_snapshot"}, "snapshot.medallion_dbt_spark.customeraddress_snapshot": {"metadata": {"type": "table", "schema": "snapshots", "name": "customeraddress_snapshot", "database": "hive_metastore", "comment": null, "owner": "root"}, "columns": {"CustomerId": {"type": "integer", "index": 0, "name": "CustomerId", "comment": null}, "AddressId": {"type": "integer", "index": 1, "name": "AddressId", "comment": null}, "AddressType": {"type": "string", "index": 2, "name": "AddressType", "comment": null}, "dbt_scd_id": {"type": "string", "index": 3, "name": "dbt_scd_id", "comment": null}, "dbt_updated_at": {"type": "timestamp", "index": 4, "name": "dbt_updated_at", "comment": null}, "dbt_valid_from": {"type": "timestamp", "index": 5, "name": "dbt_valid_from", "comment": null}, "dbt_valid_to": {"type": "timestamp", "index": 6, "name": "dbt_valid_to", "comment": null}}, "stats": {"has_stats": {"id": "has_stats", "label": "Has Stats?", "value": false, "include": false, "description": "Indicates whether there are statistics for this table"}}, "unique_id": "snapshot.medallion_dbt_spark.customeraddress_snapshot"}, "snapshot.medallion_dbt_spark.product_snapshot": {"metadata": {"type": "table", "schema": "snapshots", "name": "product_snapshot", "database": "hive_metastore", "comment": null, "owner": "root"}, "columns": {"ProductID": {"type": "integer", "index": 0, "name": "ProductID", "comment": null}, "Name": {"type": "string", "index": 1, "name": "Name", "comment": null}, "ProductNumber": {"type": "string", "index": 2, "name": "ProductNumber", "comment": null}, "Color": {"type": "string", "index": 3, "name": "Color", "comment": null}, "StandardCost": {"type": "decimal(19,4)", "index": 4, "name": "StandardCost", "comment": null}, "ListPrice": {"type": "decimal(19,4)", "index": 5, "name": "ListPrice", "comment": null}, "Size": {"type": "string", "index": 6, "name": "Size", "comment": null}, "Weight": {"type": "decimal(8,2)", "index": 7, "name": "Weight", "comment": null}, "ProductCategoryID": {"type": "integer", "index": 8, "name": "ProductCategoryID", "comment": null}, "ProductModelID": {"type": "integer", "index": 9, "name": "ProductModelID", "comment": null}, "SellStartDate": {"type": "timestamp", "index": 10, "name": "SellStartDate", "comment": null}, "SellEndDate": {"type": "timestamp", "index": 11, "name": "SellEndDate", "comment": null}, "DiscontinuedDate": {"type": "timestamp", "index": 12, "name": "DiscontinuedDate", "comment": null}, "ThumbNailPhoto": {"type": "binary", "index": 13, "name": "ThumbNailPhoto", "comment": null}, "ThumbnailPhotoFileName": {"type": "string", "index": 14, "name": "ThumbnailPhotoFileName", "comment": null}, "dbt_scd_id": {"type": "string", "index": 15, "name": "dbt_scd_id", "comment": null}, "dbt_updated_at": {"type": "timestamp", "index": 16, "name": "dbt_updated_at", "comment": null}, "dbt_valid_from": {"type": "timestamp", "index": 17, "name": "dbt_valid_from", "comment": null}, "dbt_valid_to": {"type": "timestamp", "index": 18, "name": "dbt_valid_to", "comment": null}}, "stats": {"has_stats": {"id": "has_stats", "label": "Has Stats?", "value": false, "include": false, "description": "Indicates whether there are statistics for this table"}}, "unique_id": "snapshot.medallion_dbt_spark.product_snapshot"}, "snapshot.medallion_dbt_spark.productmodel_snapshot": {"metadata": {"type": "table", "schema": "snapshots", "name": "productmodel_snapshot", "database": "hive_metastore", "comment": null, "owner": "root"}, "columns": {"ProductModelID": {"type": "integer", "index": 0, "name": "ProductModelID", "comment": null}, "Name": {"type": "string", "index": 1, "name": "Name", "comment": null}, "CatalogDescription": {"type": "string", "index": 2, "name": "CatalogDescription", "comment": null}, "dbt_scd_id": {"type": "string", "index": 3, "name": "dbt_scd_id", "comment": null}, "dbt_updated_at": {"type": "timestamp", "index": 4, "name": "dbt_updated_at", "comment": null}, "dbt_valid_from": {"type": "timestamp", "index": 5, "name": "dbt_valid_from", "comment": null}, "dbt_valid_to": {"type": "timestamp", "index": 6, "name": "dbt_valid_to", "comment": null}}, "stats": {"has_stats": {"id": "has_stats", "label": "Has Stats?", "value": false, "include": false, "description": "Indicates whether there are statistics for this table"}}, "unique_id": "snapshot.medallion_dbt_spark.productmodel_snapshot"}, "snapshot.medallion_dbt_spark.salesorderdetail_snapshot": {"metadata": {"type": "table", "schema": "snapshots", "name": "salesorderdetail_snapshot", "database": "hive_metastore", "comment": null, "owner": "root"}, "columns": {"SalesOrderID": {"type": "integer", "index": 0, "name": "SalesOrderID", "comment": null}, "SalesOrderDetailID": {"type": "integer", "index": 1, "name": "SalesOrderDetailID", "comment": null}, "OrderQty": {"type": "integer", "index": 2, "name": "OrderQty", "comment": null}, "ProductID": {"type": "integer", "index": 3, "name": "ProductID", "comment": null}, "UnitPrice": {"type": "decimal(19,4)", "index": 4, "name": "UnitPrice", "comment": null}, "UnitPriceDiscount": {"type": "decimal(19,4)", "index": 5, "name": "UnitPriceDiscount", "comment": null}, "LineTotal": {"type": "decimal(38,6)", "index": 6, "name": "LineTotal", "comment": null}, "dbt_scd_id": {"type": "string", "index": 7, "name": "dbt_scd_id", "comment": null}, "dbt_updated_at": {"type": "timestamp", "index": 8, "name": "dbt_updated_at", "comment": null}, "dbt_valid_from": {"type": "timestamp", "index": 9, "name": "dbt_valid_from", "comment": null}, "dbt_valid_to": {"type": "timestamp", "index": 10, "name": "dbt_valid_to", "comment": null}}, "stats": {"has_stats": {"id": "has_stats", "label": "Has Stats?", "value": false, "include": false, "description": "Indicates whether there are statistics for this table"}}, "unique_id": "snapshot.medallion_dbt_spark.salesorderdetail_snapshot"}, "snapshot.medallion_dbt_spark.salesorderheader_snapshot": {"metadata": {"type": "table", "schema": "snapshots", "name": "salesorderheader_snapshot", "database": "hive_metastore", "comment": null, "owner": "root"}, "columns": {"SalesOrderID": {"type": "integer", "index": 0, "name": "SalesOrderID", "comment": null}, "RevisionNumber": {"type": "integer", "index": 1, "name": "RevisionNumber", "comment": null}, "OrderDate": {"type": "timestamp", "index": 2, "name": "OrderDate", "comment": null}, "DueDate": {"type": "timestamp", "index": 3, "name": "DueDate", "comment": null}, "ShipDate": {"type": "timestamp", "index": 4, "name": "ShipDate", "comment": null}, "Status": {"type": "integer", "index": 5, "name": "Status", "comment": null}, "OnlineOrderFlag": {"type": "boolean", "index": 6, "name": "OnlineOrderFlag", "comment": null}, "SalesOrderNumber": {"type": "string", "index": 7, "name": "SalesOrderNumber", "comment": null}, "PurchaseOrderNumber": {"type": "string", "index": 8, "name": "PurchaseOrderNumber", "comment": null}, "AccountNumber": {"type": "string", "index": 9, "name": "AccountNumber", "comment": null}, "CustomerID": {"type": "integer", "index": 10, "name": "CustomerID", "comment": null}, "ShipToAddressID": {"type": "integer", "index": 11, "name": "ShipToAddressID", "comment": null}, "BillToAddressID": {"type": "integer", "index": 12, "name": "BillToAddressID", "comment": null}, "ShipMethod": {"type": "string", "index": 13, "name": "ShipMethod", "comment": null}, "CreditCardApprovalCode": {"type": "string", "index": 14, "name": "CreditCardApprovalCode", "comment": null}, "SubTotal": {"type": "decimal(19,4)", "index": 15, "name": "SubTotal", "comment": null}, "TaxAmt": {"type": "decimal(19,4)", "index": 16, "name": "TaxAmt", "comment": null}, "Freight": {"type": "decimal(19,4)", "index": 17, "name": "Freight", "comment": null}, "TotalDue": {"type": "decimal(19,4)", "index": 18, "name": "TotalDue", "comment": null}, "Comment": {"type": "string", "index": 19, "name": "Comment", "comment": null}, "dbt_scd_id": {"type": "string", "index": 20, "name": "dbt_scd_id", "comment": null}, "dbt_updated_at": {"type": "timestamp", "index": 21, "name": "dbt_updated_at", "comment": null}, "dbt_valid_from": {"type": "timestamp", "index": 22, "name": "dbt_valid_from", "comment": null}, "dbt_valid_to": {"type": "timestamp", "index": 23, "name": "dbt_valid_to", "comment": null}}, "stats": {"has_stats": {"id": "has_stats", "label": "Has Stats?", "value": false, "include": false, "description": "Indicates whether there are statistics for this table"}}, "unique_id": "snapshot.medallion_dbt_spark.salesorderheader_snapshot"}}, "sources": {"source.medallion_dbt_spark.saleslt.address": {"metadata": {"type": "table", "schema": "saleslt", "name": "address", "database": "hive_metastore", "comment": null, "owner": "root"}, "columns": {"AddressID": {"type": "integer", "index": 0, "name": "AddressID", "comment": null}, "AddressLine1": {"type": "string", "index": 1, "name": "AddressLine1", "comment": null}, "AddressLine2": {"type": "string", "index": 2, "name": "AddressLine2", "comment": null}, "City": {"type": "string", "index": 3, "name": "City", "comment": null}, "StateProvince": {"type": "string", "index": 4, "name": "StateProvince", "comment": null}, "CountryRegion": {"type": "string", "index": 5, "name": "CountryRegion", "comment": null}, "PostalCode": {"type": "string", "index": 6, "name": "PostalCode", "comment": null}, "rowguid": {"type": "string", "index": 7, "name": "rowguid", "comment": null}, "ModifiedDate": {"type": "timestamp", "index": 8, "name": "ModifiedDate", "comment": null}}, "stats": {"has_stats": {"id": "has_stats", "label": "Has Stats?", "value": false, "include": false, "description": "Indicates whether there are statistics for this table"}}, "unique_id": "source.medallion_dbt_spark.saleslt.address"}, "source.medallion_dbt_spark.saleslt.customer": {"metadata": {"type": "table", "schema": "saleslt", "name": "customer", "database": "hive_metastore", "comment": null, "owner": "root"}, "columns": {"CustomerID": {"type": "integer", "index": 0, "name": "CustomerID", "comment": null}, "NameStyle": {"type": "boolean", "index": 1, "name": "NameStyle", "comment": null}, "Title": {"type": "string", "index": 2, "name": "Title", "comment": null}, "FirstName": {"type": "string", "index": 3, "name": "FirstName", "comment": null}, "MiddleName": {"type": "string", "index": 4, "name": "MiddleName", "comment": null}, "LastName": {"type": "string", "index": 5, "name": "LastName", "comment": null}, "Suffix": {"type": "string", "index": 6, "name": "Suffix", "comment": null}, "CompanyName": {"type": "string", "index": 7, "name": "CompanyName", "comment": null}, "SalesPerson": {"type": "string", "index": 8, "name": "SalesPerson", "comment": null}, "EmailAddress": {"type": "string", "index": 9, "name": "EmailAddress", "comment": null}, "Phone": {"type": "string", "index": 10, "name": "Phone", "comment": null}, "PasswordHash": {"type": "string", "index": 11, "name": "PasswordHash", "comment": null}, "PasswordSalt": {"type": "string", "index": 12, "name": "PasswordSalt", "comment": null}, "rowguid": {"type": "string", "index": 13, "name": "rowguid", "comment": null}, "ModifiedDate": {"type": "timestamp", "index": 14, "name": "ModifiedDate", "comment": null}}, "stats": {"has_stats": {"id": "has_stats", "label": "Has Stats?", "value": false, "include": false, "description": "Indicates whether there are statistics for this table"}}, "unique_id": "source.medallion_dbt_spark.saleslt.customer"}, "source.medallion_dbt_spark.saleslt.customeraddress": {"metadata": {"type": "table", "schema": "saleslt", "name": "customeraddress", "database": "hive_metastore", "comment": null, "owner": "root"}, "columns": {"CustomerID": {"type": "integer", "index": 0, "name": "CustomerID", "comment": null}, "AddressID": {"type": "integer", "index": 1, "name": "AddressID", "comment": null}, "AddressType": {"type": "string", "index": 2, "name": "AddressType", "comment": null}, "rowguid": {"type": "string", "index": 3, "name": "rowguid", "comment": null}, "ModifiedDate": {"type": "timestamp", "index": 4, "name": "ModifiedDate", "comment": null}}, "stats": {"has_stats": {"id": "has_stats", "label": "Has Stats?", "value": false, "include": false, "description": "Indicates whether there are statistics for this table"}}, "unique_id": "source.medallion_dbt_spark.saleslt.customeraddress"}, "source.medallion_dbt_spark.saleslt.product": {"metadata": {"type": "table", "schema": "saleslt", "name": "product", "database": "hive_metastore", "comment": null, "owner": "root"}, "columns": {"ProductID": {"type": "integer", "index": 0, "name": "ProductID", "comment": null}, "Name": {"type": "string", "index": 1, "name": "Name", "comment": null}, "ProductNumber": {"type": "string", "index": 2, "name": "ProductNumber", "comment": null}, "Color": {"type": "string", "index": 3, "name": "Color", "comment": null}, "StandardCost": {"type": "decimal(19,4)", "index": 4, "name": "StandardCost", "comment": null}, "ListPrice": {"type": "decimal(19,4)", "index": 5, "name": "ListPrice", "comment": null}, "Size": {"type": "string", "index": 6, "name": "Size", "comment": null}, "Weight": {"type": "decimal(8,2)", "index": 7, "name": "Weight", "comment": null}, "ProductCategoryID": {"type": "integer", "index": 8, "name": "ProductCategoryID", "comment": null}, "ProductModelID": {"type": "integer", "index": 9, "name": "ProductModelID", "comment": null}, "SellStartDate": {"type": "timestamp", "index": 10, "name": "SellStartDate", "comment": null}, "SellEndDate": {"type": "timestamp", "index": 11, "name": "SellEndDate", "comment": null}, "DiscontinuedDate": {"type": "timestamp", "index": 12, "name": "DiscontinuedDate", "comment": null}, "ThumbNailPhoto": {"type": "binary", "index": 13, "name": "ThumbNailPhoto", "comment": null}, "ThumbnailPhotoFileName": {"type": "string", "index": 14, "name": "ThumbnailPhotoFileName", "comment": null}, "rowguid": {"type": "string", "index": 15, "name": "rowguid", "comment": null}, "ModifiedDate": {"type": "timestamp", "index": 16, "name": "ModifiedDate", "comment": null}}, "stats": {"has_stats": {"id": "has_stats", "label": "Has Stats?", "value": false, "include": false, "description": "Indicates whether there are statistics for this table"}}, "unique_id": "source.medallion_dbt_spark.saleslt.product"}, "source.medallion_dbt_spark.saleslt.productcategory": {"metadata": {"type": "table", "schema": "saleslt", "name": "productcategory", "database": "hive_metastore", "comment": null, "owner": "root"}, "columns": {"ProductCategoryID": {"type": "integer", "index": 0, "name": "ProductCategoryID", "comment": null}, "ParentProductCategoryID": {"type": "integer", "index": 1, "name": "ParentProductCategoryID", "comment": null}, "Name": {"type": "string", "index": 2, "name": "Name", "comment": null}, "rowguid": {"type": "string", "index": 3, "name": "rowguid", "comment": null}, "ModifiedDate": {"type": "timestamp", "index": 4, "name": "ModifiedDate", "comment": null}}, "stats": {"has_stats": {"id": "has_stats", "label": "Has Stats?", "value": false, "include": false, "description": "Indicates whether there are statistics for this table"}}, "unique_id": "source.medallion_dbt_spark.saleslt.productcategory"}, "source.medallion_dbt_spark.saleslt.productdescription": {"metadata": {"type": "table", "schema": "saleslt", "name": "productdescription", "database": "hive_metastore", "comment": null, "owner": "root"}, "columns": {"ProductDescriptionID": {"type": "integer", "index": 0, "name": "ProductDescriptionID", "comment": null}, "Description": {"type": "string", "index": 1, "name": "Description", "comment": null}, "rowguid": {"type": "string", "index": 2, "name": "rowguid", "comment": null}, "ModifiedDate": {"type": "timestamp", "index": 3, "name": "ModifiedDate", "comment": null}}, "stats": {"has_stats": {"id": "has_stats", "label": "Has Stats?", "value": false, "include": false, "description": "Indicates whether there are statistics for this table"}}, "unique_id": "source.medallion_dbt_spark.saleslt.productdescription"}, "source.medallion_dbt_spark.saleslt.productmodel": {"metadata": {"type": "table", "schema": "saleslt", "name": "productmodel", "database": "hive_metastore", "comment": null, "owner": "root"}, "columns": {"ProductModelID": {"type": "integer", "index": 0, "name": "ProductModelID", "comment": null}, "Name": {"type": "string", "index": 1, "name": "Name", "comment": null}, "CatalogDescription": {"type": "string", "index": 2, "name": "CatalogDescription", "comment": null}, "rowguid": {"type": "string", "index": 3, "name": "rowguid", "comment": null}, "ModifiedDate": {"type": "timestamp", "index": 4, "name": "ModifiedDate", "comment": null}}, "stats": {"has_stats": {"id": "has_stats", "label": "Has Stats?", "value": false, "include": false, "description": "Indicates whether there are statistics for this table"}}, "unique_id": "source.medallion_dbt_spark.saleslt.productmodel"}, "source.medallion_dbt_spark.saleslt.salesorderdetail": {"metadata": {"type": "table", "schema": "saleslt", "name": "salesorderdetail", "database": "hive_metastore", "comment": null, "owner": "root"}, "columns": {"SalesOrderID": {"type": "integer", "index": 0, "name": "SalesOrderID", "comment": null}, "SalesOrderDetailID": {"type": "integer", "index": 1, "name": "SalesOrderDetailID", "comment": null}, "OrderQty": {"type": "integer", "index": 2, "name": "OrderQty", "comment": null}, "ProductID": {"type": "integer", "index": 3, "name": "ProductID", "comment": null}, "UnitPrice": {"type": "decimal(19,4)", "index": 4, "name": "UnitPrice", "comment": null}, "UnitPriceDiscount": {"type": "decimal(19,4)", "index": 5, "name": "UnitPriceDiscount", "comment": null}, "LineTotal": {"type": "decimal(38,6)", "index": 6, "name": "LineTotal", "comment": null}, "rowguid": {"type": "string", "index": 7, "name": "rowguid", "comment": null}, "ModifiedDate": {"type": "timestamp", "index": 8, "name": "ModifiedDate", "comment": null}}, "stats": {"has_stats": {"id": "has_stats", "label": "Has Stats?", "value": false, "include": false, "description": "Indicates whether there are statistics for this table"}}, "unique_id": "source.medallion_dbt_spark.saleslt.salesorderdetail"}, "source.medallion_dbt_spark.saleslt.salesorderheader": {"metadata": {"type": "table", "schema": "saleslt", "name": "salesorderheader", "database": "hive_metastore", "comment": null, "owner": "root"}, "columns": {"SalesOrderID": {"type": "integer", "index": 0, "name": "SalesOrderID", "comment": null}, "RevisionNumber": {"type": "integer", "index": 1, "name": "RevisionNumber", "comment": null}, "OrderDate": {"type": "timestamp", "index": 2, "name": "OrderDate", "comment": null}, "DueDate": {"type": "timestamp", "index": 3, "name": "DueDate", "comment": null}, "ShipDate": {"type": "timestamp", "index": 4, "name": "ShipDate", "comment": null}, "Status": {"type": "integer", "index": 5, "name": "Status", "comment": null}, "OnlineOrderFlag": {"type": "boolean", "index": 6, "name": "OnlineOrderFlag", "comment": null}, "SalesOrderNumber": {"type": "string", "index": 7, "name": "SalesOrderNumber", "comment": null}, "PurchaseOrderNumber": {"type": "string", "index": 8, "name": "PurchaseOrderNumber", "comment": null}, "AccountNumber": {"type": "string", "index": 9, "name": "AccountNumber", "comment": null}, "CustomerID": {"type": "integer", "index": 10, "name": "CustomerID", "comment": null}, "ShipToAddressID": {"type": "integer", "index": 11, "name": "ShipToAddressID", "comment": null}, "BillToAddressID": {"type": "integer", "index": 12, "name": "BillToAddressID", "comment": null}, "ShipMethod": {"type": "string", "index": 13, "name": "ShipMethod", "comment": null}, "CreditCardApprovalCode": {"type": "string", "index": 14, "name": "CreditCardApprovalCode", "comment": null}, "SubTotal": {"type": "decimal(19,4)", "index": 15, "name": "SubTotal", "comment": null}, "TaxAmt": {"type": "decimal(19,4)", "index": 16, "name": "TaxAmt", "comment": null}, "Freight": {"type": "decimal(19,4)", "index": 17, "name": "Freight", "comment": null}, "TotalDue": {"type": "decimal(19,4)", "index": 18, "name": "TotalDue", "comment": null}, "Comment": {"type": "string", "index": 19, "name": "Comment", "comment": null}, "rowguid": {"type": "string", "index": 20, "name": "rowguid", "comment": null}, "ModifiedDate": {"type": "timestamp", "index": 21, "name": "ModifiedDate", "comment": null}}, "stats": {"has_stats": {"id": "has_stats", "label": "Has Stats?", "value": false, "include": false, "description": "Indicates whether there are statistics for this table"}}, "unique_id": "source.medallion_dbt_spark.saleslt.salesorderheader"}}, "errors": null}